cz_convention.py
cz_convention-2.0.1.dist-info/LICENSE
cz_convention-2.0.1.dist-info/METADATA
cz_convention-2.0.1.dist-info/WHEEL
cz_convention-2.0.1.dist-info/entry_points.txt
cz_convention-2.0.1.dist-info/top_level.txt
cz_convention-2.0.1.dist-info/RECORD
