Metadata-Version: 2.1
Name: cz_convention
Version: 2.0.1
Summary: Extend the commitizen tools to create conventional commits and CHANGELOG that link to git providers.
Home-page: https://github.com/evanhongo/cz-convention
Author: evanhongo
Author-email: evanhongo@gmail.com
License: MIT
License-File: LICENSE
Requires-Dist: commitizen
